{
 "cells": [
  {
   "cell_type": "code",
   "execution_count": 1,
   "metadata": {},
   "outputs": [],
   "source": [
    "import dis # Used to disassembles code objects\n",
    "import inspect # Used to inspect dis methods"
   ]
  },
  {
   "cell_type": "code",
   "execution_count": 2,
   "metadata": {},
   "outputs": [
    {
     "name": "stdout",
     "output_type": "stream",
     "text": [
      "Disassemble classes, methods, functions, generators, or code.\n",
      "\n",
      "    With no argument, disassemble the last traceback.\n",
      "\n",
      "    \n"
     ]
    }
   ],
   "source": [
    "print(dis.dis.__doc__)"
   ]
  },
  {
   "cell_type": "code",
   "execution_count": 14,
   "metadata": {},
   "outputs": [],
   "source": [
    "def adder(x, y):\n",
    "    return x + y\n",
    "\n",
    "def subtract(x, y):\n",
    "    return x - y\n",
    "\n",
    "def multiply(x, y):\n",
    "    return x * y\n",
    "\n",
    "def divide(x, y):\n",
    "    return x / y\n",
    "\n",
    "def floorDivide(x, y):\n",
    "    return x // y\n",
    "\n",
    "def power(x, y):\n",
    "    return x ** y\n",
    "\n",
    "def root(x, y):\n",
    "    return sqrt(x, y)"
   ]
  },
  {
   "cell_type": "code",
   "execution_count": 51,
   "metadata": {},
   "outputs": [],
   "source": [
    "def displayAssembly(funcs):\n",
    "    for func in funcs:\n",
    "        if callable(func):\n",
    "            print(func)\n",
    "            print(dis.dis(func), \"\\n\\n\")"
   ]
  },
  {
   "cell_type": "code",
   "execution_count": 53,
   "metadata": {},
   "outputs": [
    {
     "name": "stdout",
     "output_type": "stream",
     "text": [
      "<function adder at 0x00000227732FF510>\n",
      "  2           0 LOAD_FAST                0 (x)\n",
      "              2 LOAD_FAST                1 (y)\n",
      "              4 BINARY_ADD\n",
      "              6 RETURN_VALUE\n",
      "None \n",
      "\n",
      "\n",
      "<function subtract at 0x00000227732FFF28>\n",
      "  5           0 LOAD_FAST                0 (x)\n",
      "              2 LOAD_FAST                1 (y)\n",
      "              4 BINARY_SUBTRACT\n",
      "              6 RETURN_VALUE\n",
      "None \n",
      "\n",
      "\n",
      "<function multiply at 0x00000227732FF378>\n",
      "  8           0 LOAD_FAST                0 (x)\n",
      "              2 LOAD_FAST                1 (y)\n",
      "              4 BINARY_MULTIPLY\n",
      "              6 RETURN_VALUE\n",
      "None \n",
      "\n",
      "\n",
      "<function divide at 0x00000227732FFEA0>\n",
      " 11           0 LOAD_FAST                0 (x)\n",
      "              2 LOAD_FAST                1 (y)\n",
      "              4 BINARY_TRUE_DIVIDE\n",
      "              6 RETURN_VALUE\n",
      "None \n",
      "\n",
      "\n",
      "<function floorDivide at 0x00000227732FF6A8>\n",
      " 14           0 LOAD_FAST                0 (x)\n",
      "              2 LOAD_FAST                1 (y)\n",
      "              4 BINARY_FLOOR_DIVIDE\n",
      "              6 RETURN_VALUE\n",
      "None \n",
      "\n",
      "\n",
      "<function power at 0x00000227732FFD90>\n",
      " 17           0 LOAD_FAST                0 (x)\n",
      "              2 LOAD_FAST                1 (y)\n",
      "              4 BINARY_POWER\n",
      "              6 RETURN_VALUE\n",
      "None \n",
      "\n",
      "\n",
      "<function root at 0x00000227732FF730>\n",
      " 20           0 LOAD_GLOBAL              0 (sqrt)\n",
      "              2 LOAD_FAST                0 (x)\n",
      "              4 LOAD_FAST                1 (y)\n",
      "              6 CALL_FUNCTION            2\n",
      "              8 RETURN_VALUE\n",
      "None \n",
      "\n",
      "\n"
     ]
    }
   ],
   "source": [
    "displayAssembly([adder, subtract, multiply, divide, floorDivide, power, root])"
   ]
  },
  {
   "cell_type": "code",
   "execution_count": 54,
   "metadata": {},
   "outputs": [],
   "source": [
    "def recursiveMultiply(x, y):\n",
    "    if y == 1:\n",
    "        return x\n",
    "    recursiveMultiply(x + x, y - 1)\n",
    "    \n",
    "def recursivePower(x, y):\n",
    "    if y == 0:\n",
    "        return x\n",
    "    recursivePower(recursiveMultiply(x, y), y-1)"
   ]
  },
  {
   "cell_type": "code",
   "execution_count": 55,
   "metadata": {},
   "outputs": [
    {
     "name": "stdout",
     "output_type": "stream",
     "text": [
      "<function recursiveMultiply at 0x00000227745267B8>\n",
      "  2           0 LOAD_FAST                1 (y)\n",
      "              2 LOAD_CONST               1 (1)\n",
      "              4 COMPARE_OP               2 (==)\n",
      "              6 POP_JUMP_IF_FALSE       12\n",
      "\n",
      "  3           8 LOAD_FAST                0 (x)\n",
      "             10 RETURN_VALUE\n",
      "\n",
      "  4     >>   12 LOAD_GLOBAL              0 (recursiveMultiply)\n",
      "             14 LOAD_FAST                0 (x)\n",
      "             16 LOAD_FAST                0 (x)\n",
      "             18 BINARY_ADD\n",
      "             20 LOAD_FAST                1 (y)\n",
      "             22 LOAD_CONST               1 (1)\n",
      "             24 BINARY_SUBTRACT\n",
      "             26 CALL_FUNCTION            2\n",
      "             28 POP_TOP\n",
      "             30 LOAD_CONST               0 (None)\n",
      "             32 RETURN_VALUE\n",
      "None \n",
      "\n",
      "\n",
      "<function recursivePower at 0x0000022773327E18>\n",
      "  7           0 LOAD_FAST                1 (y)\n",
      "              2 LOAD_CONST               1 (0)\n",
      "              4 COMPARE_OP               2 (==)\n",
      "              6 POP_JUMP_IF_FALSE       12\n",
      "\n",
      "  8           8 LOAD_FAST                0 (x)\n",
      "             10 RETURN_VALUE\n",
      "\n",
      "  9     >>   12 LOAD_GLOBAL              0 (recursivePower)\n",
      "             14 LOAD_GLOBAL              1 (recursiveMultiply)\n",
      "             16 LOAD_FAST                0 (x)\n",
      "             18 LOAD_FAST                1 (y)\n",
      "             20 CALL_FUNCTION            2\n",
      "             22 LOAD_FAST                1 (y)\n",
      "             24 LOAD_CONST               2 (1)\n",
      "             26 BINARY_SUBTRACT\n",
      "             28 CALL_FUNCTION            2\n",
      "             30 POP_TOP\n",
      "             32 LOAD_CONST               0 (None)\n",
      "             34 RETURN_VALUE\n",
      "None \n",
      "\n",
      "\n"
     ]
    }
   ],
   "source": [
    "displayAssembly([recursiveMultiply, recursivePower])"
   ]
  },
  {
   "cell_type": "code",
   "execution_count": 75,
   "metadata": {},
   "outputs": [],
   "source": [
    "def whileloop():\n",
    "    x = 0\n",
    "    while (x % 100) != 0:\n",
    "        print(x)\n",
    "        x+=1\n",
    "\n",
    "def forloop():\n",
    "    for _ in range(10):\n",
    "        pass"
   ]
  },
  {
   "cell_type": "code",
   "execution_count": 76,
   "metadata": {},
   "outputs": [
    {
     "name": "stdout",
     "output_type": "stream",
     "text": [
      "<function whileloop at 0x0000022774526AE8>\n",
      "  2           0 LOAD_CONST               1 (0)\n",
      "              2 STORE_FAST               0 (x)\n",
      "\n",
      "  3           4 SETUP_LOOP              32 (to 38)\n",
      "        >>    6 LOAD_FAST                0 (x)\n",
      "              8 LOAD_CONST               2 (100)\n",
      "             10 BINARY_MODULO\n",
      "             12 LOAD_CONST               1 (0)\n",
      "             14 COMPARE_OP               3 (!=)\n",
      "             16 POP_JUMP_IF_FALSE       36\n",
      "\n",
      "  4          18 LOAD_GLOBAL              0 (print)\n",
      "             20 LOAD_FAST                0 (x)\n",
      "             22 CALL_FUNCTION            1\n",
      "             24 POP_TOP\n",
      "\n",
      "  5          26 LOAD_FAST                0 (x)\n",
      "             28 LOAD_CONST               3 (1)\n",
      "             30 INPLACE_ADD\n",
      "             32 STORE_FAST               0 (x)\n",
      "             34 JUMP_ABSOLUTE            6\n",
      "        >>   36 POP_BLOCK\n",
      "        >>   38 LOAD_CONST               0 (None)\n",
      "             40 RETURN_VALUE\n",
      "None \n",
      "\n",
      "\n",
      "<function forLoop at 0x0000022774526730>\n",
      "  8           0 SETUP_LOOP              16 (to 18)\n",
      "              2 LOAD_GLOBAL              0 (range)\n",
      "              4 LOAD_CONST               1 (10)\n",
      "              6 CALL_FUNCTION            1\n",
      "              8 GET_ITER\n",
      "        >>   10 FOR_ITER                 4 (to 16)\n",
      "             12 STORE_FAST               0 (_)\n",
      "\n",
      "  9          14 JUMP_ABSOLUTE           10\n",
      "        >>   16 POP_BLOCK\n",
      "        >>   18 LOAD_CONST               0 (None)\n",
      "             20 RETURN_VALUE\n",
      "None \n",
      "\n",
      "\n"
     ]
    }
   ],
   "source": [
    "displayAssembly([whileloop, forLoop])"
   ]
  },
  {
   "cell_type": "code",
   "execution_count": 84,
   "metadata": {},
   "outputs": [],
   "source": [
    "def bad():\n",
    "    bad()\n",
    "\n",
    "def generator():\n",
    "    for i in range(10):\n",
    "        yield i"
   ]
  },
  {
   "cell_type": "code",
   "execution_count": 92,
   "metadata": {},
   "outputs": [
    {
     "name": "stdout",
     "output_type": "stream",
     "text": [
      "<function bad at 0x0000022774526488>\n",
      "  2           0 LOAD_GLOBAL              0 (bad)\n",
      "              2 CALL_FUNCTION            0\n",
      "              4 POP_TOP\n",
      "              6 LOAD_CONST               0 (None)\n",
      "              8 RETURN_VALUE\n",
      "None \n",
      "\n",
      "\n",
      "<function generator at 0x0000022774526620>\n",
      "  5           0 SETUP_LOOP              22 (to 24)\n",
      "              2 LOAD_GLOBAL              0 (range)\n",
      "              4 LOAD_CONST               1 (10)\n",
      "              6 CALL_FUNCTION            1\n",
      "              8 GET_ITER\n",
      "        >>   10 FOR_ITER                10 (to 22)\n",
      "             12 STORE_FAST               0 (i)\n",
      "\n",
      "  6          14 LOAD_FAST                0 (i)\n",
      "             16 YIELD_VALUE\n",
      "             18 POP_TOP\n",
      "             20 JUMP_ABSOLUTE           10\n",
      "        >>   22 POP_BLOCK\n",
      "        >>   24 LOAD_CONST               0 (None)\n",
      "             26 RETURN_VALUE\n",
      "None \n",
      "\n",
      "\n"
     ]
    }
   ],
   "source": [
    "displayAssembly([bad, generator])"
   ]
  },
  {
   "cell_type": "code",
   "execution_count": 80,
   "metadata": {},
   "outputs": [
    {
     "name": "stdout",
     "output_type": "stream",
     "text": [
      "<function displayAssembly at 0x0000022774526D90>\n",
      "  2           0 SETUP_LOOP              44 (to 46)\n",
      "              2 LOAD_FAST                0 (funcs)\n",
      "              4 GET_ITER\n",
      "        >>    6 FOR_ITER                36 (to 44)\n",
      "              8 STORE_FAST               1 (func)\n",
      "\n",
      "  3          10 LOAD_GLOBAL              0 (callable)\n",
      "             12 LOAD_FAST                1 (func)\n",
      "             14 CALL_FUNCTION            1\n",
      "             16 POP_JUMP_IF_FALSE        6\n",
      "\n",
      "  4          18 LOAD_GLOBAL              1 (print)\n",
      "             20 LOAD_FAST                1 (func)\n",
      "             22 CALL_FUNCTION            1\n",
      "             24 POP_TOP\n",
      "\n",
      "  5          26 LOAD_GLOBAL              1 (print)\n",
      "             28 LOAD_GLOBAL              2 (dis)\n",
      "             30 LOAD_ATTR                2 (dis)\n",
      "             32 LOAD_FAST                1 (func)\n",
      "             34 CALL_FUNCTION            1\n",
      "             36 LOAD_CONST               1 ('\\n\\n')\n",
      "             38 CALL_FUNCTION            2\n",
      "             40 POP_TOP\n",
      "             42 JUMP_ABSOLUTE            6\n",
      "        >>   44 POP_BLOCK\n",
      "        >>   46 LOAD_CONST               0 (None)\n",
      "             48 RETURN_VALUE\n",
      "None \n",
      "\n",
      "\n"
     ]
    }
   ],
   "source": [
    "displayAssembly([displayAssembly])"
   ]
  },
  {
   "cell_type": "code",
   "execution_count": 101,
   "metadata": {},
   "outputs": [
    {
     "name": "stdout",
     "output_type": "stream",
     "text": [
      "Name:              bad\n",
      "Filename:          <ipython-input-84-ff8d7dc461fb>\n",
      "Argument count:    0\n",
      "Kw-only arguments: 0\n",
      "Number of locals:  0\n",
      "Stack size:        1\n",
      "Flags:             OPTIMIZED, NEWLOCALS, NOFREE\n",
      "Constants:\n",
      "   0: None\n",
      "Names:\n",
      "   0: bad\n",
      "None \n",
      "\n",
      "\n",
      "Name:              generator\n",
      "Filename:          <ipython-input-84-ff8d7dc461fb>\n",
      "Argument count:    0\n",
      "Kw-only arguments: 0\n",
      "Number of locals:  1\n",
      "Stack size:        2\n",
      "Flags:             OPTIMIZED, NEWLOCALS, GENERATOR, NOFREE\n",
      "Constants:\n",
      "   0: None\n",
      "   1: 10\n",
      "Names:\n",
      "   0: range\n",
      "Variable names:\n",
      "   0: i\n",
      "None \n",
      "\n",
      "\n"
     ]
    }
   ],
   "source": [
    "for func in [bad, generator]:\n",
    "    print(dis.show_code(func), '\\n\\n')"
   ]
  },
  {
   "cell_type": "code",
   "execution_count": 67,
   "metadata": {},
   "outputs": [],
   "source": [
    "functions = [member for member in inspect.getmembers(dis) if inspect.isfunction(member[1])] #Gets all functions of module (name, address)"
   ]
  },
  {
   "cell_type": "code",
   "execution_count": 52,
   "metadata": {},
   "outputs": [
    {
     "name": "stdout",
     "output_type": "stream",
     "text": [
      "_disassemble_bytes\n",
      "None\n",
      "____________________________________________________________________________________________________\n",
      "_disassemble_str\n",
      "Compile the source string, then disassemble the code object.\n",
      "____________________________________________________________________________________________________\n",
      "_format_code_info\n",
      "None\n",
      "____________________________________________________________________________________________________\n",
      "_get_code_object\n",
      "Helper to handle methods, functions, generators, strings and raw code objects\n",
      "____________________________________________________________________________________________________\n",
      "_get_const_info\n",
      "Helper to get optional details about const references\n",
      "\n",
      "       Returns the dereferenced constant and its repr if the constant\n",
      "       list is defined.\n",
      "       Otherwise returns the constant index and its repr().\n",
      "    \n",
      "____________________________________________________________________________________________________\n",
      "_get_instructions_bytes\n",
      "Iterate over the instructions in a bytecode string.\n",
      "\n",
      "    Generates a sequence of Instruction namedtuples giving the details of each\n",
      "    opcode.  Additional information about the code's runtime environment\n",
      "    (e.g. variable names, constants) can be specified using optional\n",
      "    arguments.\n",
      "\n",
      "    \n",
      "____________________________________________________________________________________________________\n",
      "_get_name_info\n",
      "Helper to get optional details about named references\n",
      "\n",
      "       Returns the dereferenced name as both value and repr if the name\n",
      "       list is defined.\n",
      "       Otherwise returns the name index and its repr().\n",
      "    \n",
      "____________________________________________________________________________________________________\n",
      "_test\n",
      "Simple test program to disassemble a file.\n",
      "____________________________________________________________________________________________________\n",
      "_try_compile\n",
      "Attempts to compile the given source, first as an expression and\n",
      "       then as a statement if the first approach fails.\n",
      "\n",
      "       Utility function to accept strings in functions that otherwise\n",
      "       expect code objects\n",
      "    \n",
      "____________________________________________________________________________________________________\n",
      "_unpack_opargs\n",
      "None\n",
      "____________________________________________________________________________________________________\n",
      "code_info\n",
      "Formatted details of methods, functions, or code.\n",
      "____________________________________________________________________________________________________\n",
      "dis\n",
      "Disassemble classes, methods, functions, generators, or code.\n",
      "\n",
      "    With no argument, disassemble the last traceback.\n",
      "\n",
      "    \n",
      "____________________________________________________________________________________________________\n",
      "disassemble\n",
      "Disassemble a code object.\n",
      "____________________________________________________________________________________________________\n",
      "disco\n",
      "Disassemble a code object.\n",
      "____________________________________________________________________________________________________\n",
      "distb\n",
      "Disassemble a traceback (default: last traceback).\n",
      "____________________________________________________________________________________________________\n",
      "findlabels\n",
      "Detect all offsets in a byte code which are jump targets.\n",
      "\n",
      "    Return the list of offsets.\n",
      "\n",
      "    \n",
      "____________________________________________________________________________________________________\n",
      "findlinestarts\n",
      "Find the offsets in a byte code which are start of lines in the source.\n",
      "\n",
      "    Generate pairs (offset, lineno) as described in Python/compile.c.\n",
      "\n",
      "    \n",
      "____________________________________________________________________________________________________\n",
      "get_instructions\n",
      "Iterator for the opcodes in methods, functions or code\n",
      "\n",
      "    Generates a series of Instruction named tuples giving the details of\n",
      "    each operations in the supplied code.\n",
      "\n",
      "    If *first_line* is not None, it indicates the line number that should\n",
      "    be reported for the first source line in the disassembled code.\n",
      "    Otherwise, the source line information (if any) is taken directly from\n",
      "    the disassembled code object.\n",
      "    \n",
      "____________________________________________________________________________________________________\n",
      "pretty_flags\n",
      "Return pretty representation of code flags.\n",
      "____________________________________________________________________________________________________\n",
      "show_code\n",
      "Print details of methods, functions, or code to *file*.\n",
      "\n",
      "    If *file* is not provided, the output is printed on stdout.\n",
      "    \n",
      "____________________________________________________________________________________________________\n"
     ]
    }
   ],
   "source": [
    "for func in functions:\n",
    "    print('{}\\n{}\\n{}'.format(func[0], func[1].__doc__ , '_'*100))"
   ]
  }
 ],
 "metadata": {
  "kernelspec": {
   "display_name": "Python 3",
   "language": "python",
   "name": "python3"
  },
  "language_info": {
   "codemirror_mode": {
    "name": "ipython",
    "version": 3
   },
   "file_extension": ".py",
   "mimetype": "text/x-python",
   "name": "python",
   "nbconvert_exporter": "python",
   "pygments_lexer": "ipython3",
   "version": "3.6.0"
  }
 },
 "nbformat": 4,
 "nbformat_minor": 4
}
